{
  "columns": [
    {
      "items": [
        "Torre",
        "Cripte",
        "Fortino",
        "Tumulo di pietre",
        "Statua gigante",
        "Grotte",
        "Fogne",
        "Tempio",
        "Miniere",
        "Magione",
        "Accademia",
        "Dungeon",
        "Barrow",
        "Camera blindata",
        "Tomba",
        "Tana",
        "Nave",
        "Sancta sanctorum",
        "Insenatura",
        "Castello"
      ],
      "name": "Luogo"
    },
    {
      "items": [
        "Sarcofago",
        "Obelisco",
        "Sfera",
        "Pila di ossa",
        "Teschio",
        "Megalite",
        "Pilastri",
        "Trono",
        "Statue",
        "Pozzo",
        "Planetario",
        "Effigie",
        "Cerchio arcano",
        "Guglia",
        "Altare",
        "Fossa",
        "Fontana",
        "Arco",
        "Gabbia",
        "Braciere"
      ],
      "name": "Monumento"
    },
    {
      "items": [
        "Moneta",
        "Statuetta",
        "Gemma",
        "Amuleto",
        "Orecchino",
        "Campana",
        "Osso",
        "Ciotola",
        "Candela",
        "Anello",
        "Diadema",
        "Bracciale",
        "Pugnale",
        "Calice",
        "Chiave",
        "Lampada",
        "Spilla",
        "Teschio",
        "Maschera",
        "Collana"
      ],
      "name": "Oggetto"
    }
  ],
  "description": "Il luogo della missione potrebbe contenere monumenti o oggetti legati agli obiettivi dell'avventura.",
  "die": "1d20",
  "group": "core-adventure",
  "id": "luoghi-monumenti-oggetti",
  "name": "Luoghi, Monumenti e Oggetti",
  "order": 3,
  "source": {
    "author": "Sly Flourish",
    "url": "https://slyflourish.com/"
  }
}
