{
  "description": "Mostri di grado sfida 5 — 8.",
  "die": "1d20",
  "group": "dungeon-monsters",
  "id": "mostri-lista-7",
  "items": [
    {
      "link": "/srd/mostri/salamandra",
      "text": "Salamandra"
    },
    {
      "link": "/srd/mostri/progenie-vampirica",
      "text": "Progenie vampirica"
    },
    {
      "link": "/srd/mostri/elementale-dellacqua",
      "text": "Elementale dell'acqua"
    },
    {
      "link": "/srd/mostri/wraith",
      "text": "Wraith"
    },
    {
      "link": "/srd/mostri/xorn",
      "text": "Xorn"
    },
    {
      "link": "/srd/mostri/chimera",
      "text": "Chimera"
    },
    {
      "link": "/srd/mostri/drider",
      "text": "Drider"
    },
    {
      "link": "/srd/mostri/cacciatore-invisibile",
      "text": "Cacciatore invisibile"
    },
    {
      "link": "/srd/mostri/mago",
      "text": "Mago"
    },
    {
      "link": "/srd/mostri/medusa",
      "text": "Medusa"
    },
    {
      "link": "/srd/mostri/vrock",
      "text": "Vrock"
    },
    {
      "link": "/srd/mostri/viverna",
      "text": "Viverna"
    },
    {
      "link": "/srd/mostri/drago-bianco-giovane",
      "text": "Drago bianco giovane"
    },
    {
      "link": "/srd/mostri/oni",
      "text": "Oni"
    },
    {
      "link": "/srd/mostri/guardiano-protettore",
      "text": "Guardiano protettore"
    },
    {
      "link": "/srd/mostri/gigante-delle-pietre",
      "text": "Gigante delle pietre"
    },
    {
      "link": "/srd/mostri/drago-nero-giovane",
      "text": "Drago nero giovane"
    },
    {
      "link": "/srd/mostri/assassino",
      "text": "Assassino"
    },
    {
      "link": "/srd/mostri/diavolo-delle-catene",
      "text": "Diavolo delle catene"
    },
    {
      "link": "/srd/mostri/manto-assassino",
      "text": "Manto assassino"
    }
  ],
  "name": "Lista Mostri 7 (GS 5—8)",
  "order": 97,
  "source": {
    "author": "Sly Flourish",
    "url": "https://slyflourish.com/"
  }
}
